tftui/__init__.py
tftui/__main__.py
tftui/apis.py
tftui/constants.py
tftui/debug_log.py
tftui/modal.py
tftui/plan.py
tftui/state.py
tftui/ui.tcss
tftui-0.13.4.dist-info/LICENSE
tftui-0.13.4.dist-info/METADATA
tftui-0.13.4.dist-info/WHEEL
tftui-0.13.4.dist-info/entry_points.txt
tftui-0.13.4.dist-info/RECORD
