Metadata-Version: 2.1
Name: tftui
Version: 0.13.4
Summary: Terraform Textual User Interface
Home-page: https://github.com/idoavrah/terraform-tui
License: Apache-2.0
Keywords: terraform,tui
Author: Ido Avraham
Requires-Python: >=3.9,<4.0
Classifier: License :: OSI Approved :: Apache Software License
Classifier: Programming Language :: Python
Classifier: Programming Language :: Python :: 3
Classifier: Programming Language :: Python :: 3.9
Classifier: Programming Language :: Python :: 3.10
Classifier: Programming Language :: Python :: 3.11
Classifier: Programming Language :: Python :: 3.12
Requires-Dist: posthog (>=3.1.0,<4.0.0)
Requires-Dist: pyperclip (>=1.8.2,<2.0.0)
Requires-Dist: requests (>=2.31.0,<3.0.0)
Requires-Dist: textual (>=0.44.1,<0.45.0)
Project-URL: Repository, https://github.com/idoavrah/terraform-tui
